Tests/__init__.py
Tests/hypo_strategies.py
Tests/pos_test.py
Tests/test_connexion.py
Tests/test_kola.py
Tests/utils.py
Tests/kola/__init__.py
Tests/kola/utils/__init__.py
Tests/kola/utils/test_general.py
Tests/kola/utils/test_logfunc.py
kolaBitMEXBot/__init__.py
kolaBitMEXBot/cancel_all.py
kolaBitMEXBot/multi_kola.py
kolaBitMEXBot/pos_test.py
kolaBitMEXBot/run_multi_kola.py
kolaBitMEXBot/kola/__init__.py
kolaBitMEXBot/kola/bargain.py
kolaBitMEXBot/kola/chronos.py
kolaBitMEXBot/kola/custom_bitmex.py
kolaBitMEXBot/kola/dummy_bitmex.py
kolaBitMEXBot/kola/kolatypes.py
kolaBitMEXBot/kola/price.py
kolaBitMEXBot/kola/secrets.py
kolaBitMEXBot/kola/settings.py
kolaBitMEXBot/kola/connexion/__init__.py
kolaBitMEXBot/kola/connexion/auth.py
kolaBitMEXBot/kola/connexion/custom_ws_thread.py
kolaBitMEXBot/kola/orders/__init__.py
kolaBitMEXBot/kola/orders/condition.py
kolaBitMEXBot/kola/orders/hookorder.py
kolaBitMEXBot/kola/orders/ordercond.py
kolaBitMEXBot/kola/orders/orders.py
kolaBitMEXBot/kola/orders/trailstop.py
kolaBitMEXBot/kola/utils/__init__.py
kolaBitMEXBot/kola/utils/argfunc.py
kolaBitMEXBot/kola/utils/conditions.py
kolaBitMEXBot/kola/utils/constantes.py
kolaBitMEXBot/kola/utils/datefunc.py
kolaBitMEXBot/kola/utils/exceptions.py
kolaBitMEXBot/kola/utils/general.py
kolaBitMEXBot/kola/utils/logfunc.py
kolaBitMEXBot/kola/utils/orderfunc.py
kolaBitMEXBot/kola/utils/pricefunc.py
kolaBitMEXBot-1.1.9.dist-info/LICENSE.txt
kolaBitMEXBot-1.1.9.dist-info/METADATA
kolaBitMEXBot-1.1.9.dist-info/WHEEL
kolaBitMEXBot-1.1.9.dist-info/entry_points.txt
kolaBitMEXBot-1.1.9.dist-info/top_level.txt
kolaBitMEXBot-1.1.9.dist-info/RECORD
